core_exceptions/__init__.py
core_exceptions/contextmanagers.py
core_exceptions/core.py
core_exceptions/decorators.py
core_exceptions/exception_types.py
core_exceptions/py.typed
turintech_exceptions-2.0.2.dist-info/METADATA
turintech_exceptions-2.0.2.dist-info/WHEEL
turintech_exceptions-2.0.2.dist-info/licenses/LICENSE
turintech_exceptions-2.0.2.dist-info/RECORD
