Metadata-Version: 2.4
Name: turintech_exceptions
Version: 2.0.2
Summary: Core exceptions for the core library
License-Expression: LicenseRef-Turing-Intelligence-Technology-EULA
License-File: LICENSE
Classifier: Development Status :: 5 - Production/Stable
Classifier: License :: Other/Proprietary License
Requires-Python: <3.14,>=3.11
Requires-Dist: turintech-data-types<3.0.0,>=2.0.0a0
Requires-Dist: turintech-logging<3.0.0,>=2.0.0a0
